scanix-2.0.0.dist-info/licenses/LICENSE
src/__init__.py
src/main.py
src/core/__init__.py
src/core/explications.py
src/core/exporter.py
src/core/scanner.py
src/screens/__init__.py
src/screens/file_select.py
src/screens/folder_select.py
src/screens/results.py
src/screens/scan_mode.py
src/screens/scanning.py
src/screens/welcome.py
src/ui/__init__.py
src/ui/app.py
src/utils/__init__.py
src/utils/file_helpers.py
src/utils/security_helpers.py
scanix-2.0.0.dist-info/METADATA
scanix-2.0.0.dist-info/WHEEL
scanix-2.0.0.dist-info/entry_points.txt
scanix-2.0.0.dist-info/top_level.txt
scanix-2.0.0.dist-info/RECORD
