Metadata-Version: 2.4
Name: scanix
Version: 2.0.0
Summary: ⚡ Fast and powerful static code security scanner - Détecte 25+ vulnérabilités OWASP
Home-page: https://github.com/Ore2025/scanix
Author: Riyad ODJOUADE
Author-email: Riyad ODJOUADE <riyadodjouade@gmail.com>
License: MIT
Project-URL: Homepage, https://github.com/Ore2025/scanix
Project-URL: Documentation, https://github.com/Ore2025/scanix#readme
Project-URL: Repository, https://github.com/Ore2025/scanix
Project-URL: Bug Tracker, https://github.com/Ore2025/scanix/issues
Keywords: security,scanner,static-analysis,vulnerability,owasp,code-security
Classifier: Development Status :: 4 - Beta
Classifier: Intended Audience :: Developers
Classifier: Topic :: Security
Classifier: License :: OSI Approved :: MIT License
Classifier: Programming Language :: Python :: 3
Classifier: Programming Language :: Python :: 3.8
Classifier: Programming Language :: Python :: 3.9
Classifier: Programming Language :: Python :: 3.10
Classifier: Programming Language :: Python :: 3.11
Classifier: Programming Language :: Python :: 3.12
Classifier: Operating System :: OS Independent
Requires-Python: >=3.8
License-File: LICENSE
Requires-Dist: textual>=0.50.0
Requires-Dist: rich>=13.7.0
Requires-Dist: python-dotenv>=1.0.0
Requires-Dist: pyyaml>=6.0.1
Dynamic: author
Dynamic: home-page
Dynamic: license-file
Dynamic: requires-python
